{
  "drivers": [
{
	"driverName": "A Murphy",
	"carNumber": "177",
	"lapsCompleted": "3811",
	"lapsLed": "1281",
	"dnfs": "1",
	"racesLed": "20",
	"startPositions":[
		"27",
		"18",
		"1",
		"1",
		"1",
		"37",
		"11",
		"8",
		"31",
		"2",
		"1",
		"40",
		"3",
		"3",
		"2",
		"1",
		"10",
		"6",
		"1",
		"17",
		"1",
		"1",
		"30",
		"1",
		"7"
	],
	"startPositionsCount": "25",
	"starts": "25",
	"finishPositions":[
		"32",
		"35",
		"20",
		"1",
		"12",
		"27",
		"2",
		"39",
		"31",
		"1",
		"1",
		"16",
		"41",
		"25",
		"1",
		"10",
		"21",
		"1",
		"23",
		"1",
		"1",
		"15",
		"39",
		"1",
		"39"
	],
	"finishPositionsCount": "25",
	"finishes": "25",
	"points": "3430"
},
{
	"driverName": "B Bodine",
	"carNumber": "11",
	"lapsCompleted": "2887",
	"lapsLed": "3",
	"dnfs": "3",
	"racesLed": "2",
	"startPositions":[
		"29",
		"27",
		"0",
		"39",
		"8",
		"0",
		"20",
		"26",
		"26",
		"26",
		"17",
		"31",
		"37",
		"0",
		"20",
		"0",
		"34",
		"38",
		"43",
		"28",
		"33",
		"11",
		"39",
		"30",
		"35"
	],
	"startPositionsCount": "25",
	"starts": "21",
	"finishPositions":[
		"31",
		"22",
		"0",
		"34",
		"17",
		"0",
		"31",
		"31",
		"39",
		"8",
		"38",
		"29",
		"20",
		"0",
		"32",
		"0",
		"35",
		"26",
		"35",
		"13",
		"27",
		"5",
		"16",
		"29",
		"34"
	],
	"finishPositionsCount": "25",
	"finishes": "21",
	"points": "1820"
},
{
	"driverName": "B Elliott",
	"carNumber": "9",
	"lapsCompleted": "3858",
	"lapsLed": "104",
	"dnfs": "0",
	"racesLed": "6",
	"startPositions":[
		"6",
		"15",
		"15",
		"2",
		"23",
		"29",
		"35",
		"13",
		"9",
		"27",
		"31",
		"6",
		"25",
		"7",
		"26",
		"39",
		"9",
		"21",
		"33",
		"20",
		"21",
		"15",
		"2",
		"26",
		"17"
	],
	"startPositionsCount": "25",
	"starts": "25",
	"finishPositions":[
		"12",
		"5",
		"9",
		"16",
		"6",
		"6",
		"4",
		"14",
		"6",
		"23",
		"17",
		"6",
		"14",
		"28",
		"9",
		"21",
		"12",
		"14",
		"9",
		"5",
		"29",
		"12",
		"28",
		"16",
		"12"
	],
	"finishPositionsCount": "25",
	"finishes": "25",
	"points": "3800"
},
{
	"driverName": "B Labonte",
	"carNumber": "18",
	"lapsCompleted": "3750",
	"lapsLed": "52",
	"dnfs": "2",
	"racesLed": "5",
	"startPositions":[
		"20",
		"1",
		"36",
		"33",
		"33",
		"24",
		"24",
		"18",
		"12",
		"6",
		"6",
		"23",
		"31",
		"29",
		"30",
		"7",
		"4",
		"13",
		"28",
		"31",
		"4",
		"4",
		"3",
		"18",
		"12"
	],
	"startPositionsCount": "25",
	"starts": "25",
	"finishPositions":[
		"13",
		"15",
		"42",
		"29",
		"7",
		"33",
		"18",
		"22",
		"17",
		"13",
		"32",
		"11",
		"7",
		"20",
		"25",
		"13",
		"17",
		"9",
		"42",
		"15",
		"20",
		"2",
		"22",
		"28",
		"36"
	],
	"finishPositionsCount": "25",
	"finishes": "25",
	"points": "2920"
},
{
	"driverName": "B Said",
	"carNumber": "67",
	"lapsCompleted": "3224",
	"lapsLed": "4",
	"dnfs": "5",
	"racesLed": "1",
	"startPositions":[
		"34",
		"10",
		"41",
		"40",
		"43",
		"20",
		"31",
		"33",
		"39",
		"1",
		"11",
		"14",
		"22",
		"35",
		"37",
		"31",
		"28",
		"39",
		"32",
		"1",
		"39",
		"40",
		"41",
		"37",
		"38"
	],
	"startPositionsCount": "25",
	"starts": "25",
	"finishPositions":[
		"23",
		"43",
		"36",
		"42",
		"37",
		"22",
		"29",
		"26",
		"32",
		"29",
		"29",
		"33",
		"19",
		"0",
		"39",
		"15",
		"14",
		"35",
		"34",
		"43",
		"32",
		"18",
		"26",
		"35",
		"30"
	],
	"finishPositionsCount": "25",
	"finishes": "24",
	"points": "1625"
},
{
	  "driverName": "B Simpson",
	  "carNumber": "193",
	  "lapsCompleted": "298",
	  "lapsLed": "0",
	  "dnfs": "2",
	  "racesLed": "0",
	"startPositions":[
		"0",
		"0",
		"0",
		"0",
		"0",
		"0",
		"0",
		"0",
		"0",
		"0",
		"42",
		"0",
		"0",
		"0",
		"0",
		"0",
		"0",
		"0",
		"0",
		"0",
		"0",
		"0",
		"0",
		"34",
		"0"
	],
	  "startPositionsCount": "25",
	  "starts": "2",
	"finishPositions":[
		"0",
		"0",
		"0",
		"0",
		"0",
		"0",
		"0",
		"0",
		"0",
		"0",
		"40",
		"0",
		"0",
		"0",
		"0",
		"0",
		"0",
		"0",
		"0",
		"0",
		"0",
		"0",
		"0",
		"41",
		"0"
	],
  	"finishPositionsCount": "25",
	  "finishes": "2",
	  "points": "35"
},
{
	"driverName": "C Gibson",
	"carNumber": "105",
	"lapsCompleted": "604",
	"lapsLed": "0",
	"dnfs": "1",
	"racesLed": "0",
	"startPositions":[
		"43",
		"0",
		"0",
		"0",
		"0",
		"0",
		"37",
		"0",
		"0",
		"0",
		"0",
		"0",
		"0",
		"0",
		"0",
		"38",
		"0",
		"0",
		"0",
		"0",
		"0",
		"43",
		"0",
		"0",
		"41"
	],
	"startPositionsCount": "25",
	"starts": "5",
	"finishPositions":[
		"27",
		"0",
		"0",
		"0",
		"0",
		"0",
		"38",
		"0",
		"0",
		"0",
		"0",
		"0",
		"0",
		"0",
		"0",
		"35",
		"0",
		"0",
		"0",
		"0",
		"0",
		"43",
		"0",
		"0",
		"37"
	],
	"finishPositionsCount": "25",
	"finishes": "5",
	"points": "195"
},
{
	"driverName": "D Blaney",
	"carNumber": "77",
	"lapsCompleted": "3803",
	"lapsLed": "28",
	"dnfs": "1",
	"racesLed": "3",
	"startPositions":[
		"9",
		"29",
		"34",
		"16",
		"5",
		"17",
		"5",
		"24",
		"13",
		"33",
		"15",
		"28",
		"33",
		"5",
		"11",
		"16",
		"27",
		"22",
		"13",
		"12",
		"14",
		"24",
		"9",
		"14",
		"24"
	],
	"startPositionsCount": "25",
	"starts": "25",
	"finishPositions":[
		"10",
		"12",
		"19",
		"22",
		"10",
		"14",
		"8",
		"13",
		"27",
		"28",
		"14",
		"10",
		"18",
		"26",
		"11",
		"27",
		"20",
		"32",
		"19",
		"10",
		"12",
		"3",
		"17",
		"6",
		"43"
	],
	"finishPositionsCount": "25",
	"finishes": "25",
	"points": "3295"
},
{
	  "driverName": "D Clough",
	  "carNumber": "117",
	  "lapsCompleted": "138",
	  "lapsLed": "0",
	  "dnfs": "2",
	  "racesLed": "0",
	"startPositions":[
		"0",
		"0",
		"0",
		"0",
		"0",
		"0",
		"0",
		"0",
		"0",
		"0",
		"0",
		"0",
		"0",
		"0",
		"0",
		"0",
		"20",
		"0",
		"40",
		"0",
		"0",
		"0",
		"0",
		"0",
		"0"
	],
	  "startPositionsCount": "25",
	  "starts": "2",
	"finishPositions":[
		"0",
		"0",
		"0",
		"0",
		"0",
		"0",
		"0",
		"0",
		"0",
		"0",
		"0",
		"0",
		"0",
		"0",
		"0",
		"0",
		"42",
		"0",
		"39",
		"0",
		"0",
		"0",
		"0",
		"0",
		"0"
	],
  	"finishPositionsCount": "25",
	  "finishes": "2",
	  "points": "35"
},
{
	"driverName": "D Earnhardt Jr.",
	"carNumber": "8",
	"lapsCompleted": "3764",
	"lapsLed": "48",
	"dnfs": "3",
	"racesLed": "5",
	"startPositions":[
		"31",
		"8",
		"6",
		"5",
		"10",
		"28",
		"10",
		"5",
		"4",
		"30",
		"41",
		"18",
		"23",
		"16",
		"4",
		"13",
		"41",
		"43",
		"17",
		"23",
		"7",
		"23",
		"21",
		"3",
		"26"
	],
	"startPositionsCount": "25",
	"starts": "25",
	"finishPositions":[
		"21",
		"40",
		"14",
		"6",
		"24",
		"12",
		"3",
		"19",
		"5",
		"35",
		"9",
		"14",
		"5",
		"2",
		"5",
		"4",
		"29",
		"13",
		"6",
		"37",
		"7",
		"33",
		"43",
		"38",
		"6"
	],
	"finishPositionsCount": "25",
	"finishes": "25",
	"points": "3310"
},
{
	  "driverName": "D Goward",
	  "carNumber": "101",
	  "lapsCompleted": "358",
	  "lapsLed": "0",
	  "dnfs": "0",
	  "racesLed": "0",
	"startPositions":[
		"0",
		"0",
		"0",
		"41",
		"0",
		"0",
		"0",
		"0",
		"0",
		"0",
		"0",
		"0",
		"0",
		"37",
		"0",
		"0",
		"0",
		"0",
		"0",
		"0",
		"0",
		"0",
		"0",
		"0",
		"0"
	],
	  "startPositionsCount": "25",
	  "starts": "2",
	"finishPositions":[
		"0",
		"0",
		"0",
		"41",
		"0",
		"0",
		"0",
		"0",
		"0",
		"0",
		"0",
		"0",
		"0",
		"38",
		"0",
		"0",
		"0",
		"0",
		"0",
		"0",
		"0",
		"0",
		"0",
		"0",
		"0"
	],
  	"finishPositionsCount": "25",
	  "finishes": "2",
	  "points": "35"
},
{
	"driverName": "D Jarrett",
	"carNumber": "88",
	"lapsCompleted": "3397",
	"lapsLed": "63",
	"dnfs": "4",
	"racesLed": "4",
	"startPositions":[
		"4",
		"23",
		"26",
		"13",
		"41",
		"23",
		"12",
		"20",
		"27",
		"13",
		"30",
		"10",
		"5",
		"40",
		"22",
		"12",
		"3",
		"2",
		"22",
		"41",
		"2",
		"20",
		"10",
		"41",
		"5"
	],
	"startPositionsCount": "25",
	"starts": "25",
	"finishPositions":[
		"1",
		"42",
		"6",
		"9",
		"11",
		"37",
		"10",
		"20",
		"42",
		"4",
		"8",
		"24",
		"2",
		"27",
		"16",
		"11",
		"1",
		"12",
		"24",
		"38",
		"5",
		"32",
		"6",
		"39",
		"15"
	],
	"finishPositionsCount": "25",
	"finishes": "25",
	"points": "3250"
},
{
	  "driverName": "D Sweet",
	  "carNumber": "128",
	  "lapsCompleted": "198",
	  "lapsLed": "0",
	  "dnfs": "0",
	  "racesLed": "0",
	"startPositions":[
		"0",
		"0",
		"0",
		"0",
		"0",
		"0",
		"0",
		"0",
		"0",
		"0",
		"0",
		"0",
		"0",
		"38",
		"0",
		"0",
		"0",
		"0",
		"0",
		"0",
		"0",
		"0",
		"0",
		"0",
		"0"
	],
	  "startPositionsCount": "25",
	  "starts": "1",
	"finishPositions":[
		"0",
		"0",
		"0",
		"0",
		"0",
		"0",
		"0",
		"0",
		"0",
		"0",
		"0",
		"0",
		"0",
		"35",
		"0",
		"0",
		"0",
		"0",
		"0",
		"0",
		"0",
		"0",
		"0",
		"0",
		"0"
	],
  	"finishPositionsCount": "25",
	  "finishes": "1",
	  "points": "35"
},
{
	"driverName": "E Sadler",
	"carNumber": "38",
	"lapsCompleted": "3760",
	"lapsLed": "0",
	"dnfs": "1",
	"racesLed": "0",
	"startPositions":[
		"37",
		"30",
		"21",
		"32",
		"42",
		"21",
		"13",
		"30",
		"6",
		"23",
		"34",
		"26",
		"17",
		"13",
		"32",
		"35",
		"39",
		"30",
		"36",
		"30",
		"32",
		"31",
		"15",
		"8",
		"28"
	],
	"startPositionsCount": "25",
	"starts": "25",
	"finishPositions":[
		"4",
		"29",
		"27",
		"28",
		"21",
		"21",
		"28",
		"28",
		"24",
		"37",
		"12",
		"37",
		"29",
		"39",
		"27",
		"9",
		"27",
		"34",
		"36",
		"41",
		"24",
		"7",
		"12",
		"19",
		"28"
	],
	"finishPositionsCount": "25",
	"finishes": "25",
	"points": "2295"
},
{
	  "driverName": "F Antippas",
	  "carNumber": "123",
	  "lapsCompleted": "250",
	  "lapsLed": "0",
	  "dnfs": "0",
	  "racesLed": "0",
	"startPositions":[
		"0",
		"0",
		"0",
		"0",
		"0",
		"0",
		"0",
		"0",
		"0",
		"0",
		"0",
		"0",
		"0",
		"0",
		"0",
		"0",
		"43",
		"0",
		"0",
		"0",
		"0",
		"0",
		"0",
		"0",
		"0"
	],
	  "startPositionsCount": "25",
	  "starts": "1",
	"finishPositions":[
		"0",
		"0",
		"0",
		"0",
		"0",
		"0",
		"0",
		"0",
		"0",
		"0",
		"0",
		"0",
		"0",
		"0",
		"0",
		"0",
		"8",
		"0",
		"0",
		"0",
		"0",
		"0",
		"0",
		"0",
		"0"
	],
  	"finishPositionsCount": "25",
	  "finishes": "1",
	  "points": "180"
},
{
	"driverName": "G Biffle",
	"carNumber": "16",
	"lapsCompleted": "3721",
	"lapsLed": "2",
	"dnfs": "2",
	"racesLed": "1",
	"startPositions":[
		"18",
		"20",
		"4",
		"17",
		"28",
		"19",
		"34",
		"39",
		"33",
		"17",
		"26",
		"29",
		"32",
		"14",
		"12",
		"5",
		"14",
		"26",
		"31",
		"0",
		"29",
		"29",
		"32",
		"17",
		"20"
	],
	"startPositionsCount": "25",
	"starts": "24",
	"finishPositions":[
		"3",
		"17",
		"22",
		"26",
		"31",
		"8",
		"42",
		"15",
		"19",
		"7",
		"24",
		"8",
		"15",
		"31",
		"33",
		"12",
		"6",
		"23",
		"17",
		"0",
		"9",
		"34",
		"21",
		"30",
		"20"
	],
	"finishPositionsCount": "25",
	"finishes": "24",
	"points": "2855"
},
{
	  "driverName": "G Grimshaw",
	  "carNumber": "162",
	  "lapsCompleted": "344",
	  "lapsLed": "0",
	  "dnfs": "0",
	  "racesLed": "0",
	"startPositions":[
		"0",
		"0",
		"0",
		"0",
		"0",
		"0",
		"0",
		"0",
		"0",
		"0",
		"0",
		"38",
		"0",
		"0",
		"0",
		"0",
		"0",
		"0",
		"0",
		"35",
		"0",
		"0",
		"43",
		"0",
		"0"
	],
	  "startPositionsCount": "25",
	  "starts": "3",
	"finishPositions":[
		"0",
		"0",
		"0",
		"0",
		"0",
		"0",
		"0",
		"0",
		"0",
		"0",
		"0",
		"42",
		"0",
		"0",
		"0",
		"0",
		"0",
		"0",
		"0",
		"31",
		"0",
		"0",
		"33",
		"0",
		"0"
	],
  	"finishPositionsCount": "25",
	  "finishes": "3",
	  "points": "130"
},
{
	  "driverName": "G Hill",
	  "carNumber": "188",
	  "lapsCompleted": "478",
	  "lapsLed": "0",
	  "dnfs": "0",
	  "racesLed": "0",
	"startPositions":[
		"0",
		"0",
		"0",
		"0",
		"38",
		"0",
		"0",
		"0",
		"0",
		"0",
		"0",
		"0",
		"0",
		"32",
		"0",
		"0",
		"0",
		"0",
		"0",
		"0",
		"40",
		"0",
		"0",
		"0",
		"0"
	],
	  "startPositionsCount": "25",
	  "starts": "3",
	"finishPositions":[
		"0",
		"0",
		"0",
		"0",
		"36",
		"0",
		"0",
		"0",
		"0",
		"0",
		"0",
		"0",
		"0",
		"32",
		"0",
		"0",
		"0",
		"0",
		"0",
		"0",
		"22",
		"0",
		"0",
		"0",
		"0"
	],
  	"finishPositionsCount": "25",
	  "finishes": "3",
	  "points": "200"
},
{
	  "driverName": "H Minh",
	  "carNumber": "148",
	  "lapsCompleted": "90",
	  "lapsLed": "0",
	  "dnfs": "0",
	  "racesLed": "0",
	"startPositions":[
		"0",
		"0",
		"0",
		"0",
		"0",
		"0",
		"0",
		"0",
		"41",
		"0",
		"0",
		"0",
		"0",
		"0",
		"0",
		"0",
		"0",
		"0",
		"0",
		"0",
		"0",
		"0",
		"0",
		"0",
		"0"
	],
	  "startPositionsCount": "25",
	  "starts": "1",
	"finishPositions":[
		"0",
		"0",
		"0",
		"0",
		"0",
		"0",
		"0",
		"0",
		"30",
		"0",
		"0",
		"0",
		"0",
		"0",
		"0",
		"0",
		"0",
		"0",
		"0",
		"0",
		"0",
		"0",
		"0",
		"0",
		"0"
	],
  	"finishPositionsCount": "25",
	  "finishes": "1",
	  "points": "70"
},
{
	  "driverName": "H Sadler",
	  "carNumber": "02",
	  "lapsCompleted": "1959",
	  "lapsLed": "0",
	  "dnfs": "4",
	  "racesLed": "0",
	"startPositions":[
		"39",
		"32",
		"0",
		"18",
		"36",
		"32",
		"0",
		"0",
		"42",
		"0",
		"0",
		"41",
		"41",
		"26",
		"38",
		"32",
		"0",
		"32",
		"37",
		"22",
		"0",
		"0",
		"40",
		"42",
		"0"
	],
	  "startPositionsCount": "25",
	  "starts": "16",
	"finishPositions":[
		"11",
		"34",
		"0",
		"33",
		"35",
		"41",
		"0",
		"0",
		"36",
		"0",
		"0",
		"35",
		"37",
		"34",
		"35",
		"41",
		"0",
		"37",
		"33",
		"24",
		"0",
		"0",
		"25",
		"32",
		"0"
	],
  	"finishPositionsCount": "25",
	  "finishes": "16",
	  "points": "875"
},
{
	"driverName": "J Andretti",
	"carNumber": "43",
	"lapsCompleted": "3720",
	"lapsLed": "2",
	"dnfs": "3",
	"racesLed": "1",
	"startPositions":[
		"30",
		"21",
		"12",
		"29",
		"19",
		"13",
		"18",
		"21",
		"36",
		"36",
		"22",
		"27",
		"4",
		"20",
		"39",
		"41",
		"36",
		"34",
		"7",
		"14",
		"27",
		"21",
		"35",
		"27",
		"37"
	],
	"startPositionsCount": "25",
	"starts": "25",
	"finishPositions":[
		"38",
		"28",
		"21",
		"32",
		"19",
		"5",
		"21",
		"27",
		"22",
		"11",
		"23",
		"26",
		"13",
		"12",
		"22",
		"19",
		"22",
		"21",
		"21",
		"18",
		"41",
		"36",
		"34",
		"27",
		"31"
	],
	"finishPositionsCount": "25",
	"finishes": "25",
	"points": "2490"
},
{
	  "driverName": "J Balkan",
	  "carNumber": "109",
	  "lapsCompleted": "515",
	  "lapsLed": "0",
	  "dnfs": "3",
	  "racesLed": "0",
	"startPositions":[
		"41",
		"41",
		"0",
		"0",
		"0",
		"0",
		"0",
		"0",
		"0",
		"0",
		"0",
		"0",
		"43",
		"0",
		"0",
		"0",
		"0",
		"0",
		"41",
		"0",
		"43",
		"0",
		"0",
		"0",
		"0"
	],
	  "startPositionsCount": "25",
	  "starts": "5",
	"finishPositions":[
		"33",
		"38",
		"0",
		"0",
		"0",
		"0",
		"0",
		"0",
		"0",
		"0",
		"0",
		"0",
		"42",
		"0",
		"0",
		"0",
		"0",
		"0",
		"38",
		"0",
		"33",
		"0",
		"0",
		"0",
		"0"
	],
  	"finishPositionsCount": "25",
	  "finishes": "5",
	  "points": "180"
},
{
	  "driverName": "J Beatty",
	  "carNumber": "121",
	  "lapsCompleted": "570",
	  "lapsLed": "0",
	  "dnfs": "0",
	  "racesLed": "0",
	"startPositions":[
		"0",
		"0",
		"35",
		"0",
		"31",
		"0",
		"0",
		"0",
		"0",
		"0",
		"0",
		"21",
		"0",
		"0",
		"0",
		"0",
		"0",
		"0",
		"0",
		"0",
		"0",
		"0",
		"42",
		"0",
		"0"
	],
	  "startPositionsCount": "25",
	  "starts": "4",
	"finishPositions":[
		"0",
		"0",
		"39",
		"0",
		"20",
		"0",
		"0",
		"0",
		"0",
		"0",
		"0",
		"34",
		"0",
		"0",
		"0",
		"0",
		"0",
		"0",
		"0",
		"0",
		"0",
		"0",
		"36",
		"0",
		"0"
	],
  	"finishPositionsCount": "25",
	  "finishes": "4",
	  "points": "235"
},
{
	"driverName": "J Benson",
	"carNumber": "10",
	"lapsCompleted": "3468",
	"lapsLed": "17",
	"dnfs": "6",
	"racesLed": "2",
	"startPositions":[
		"28",
		"36",
		"28",
		"4",
		"26",
		"25",
		"32",
		"11",
		"3",
		"29",
		"19",
		"11",
		"11",
		"12",
		"6",
		"36",
		"25",
		"28",
		"18",
		"26",
		"30",
		"37",
		"31",
		"6",
		"15"
	],
	"startPositionsCount": "25",
	"starts": "25",
	"finishPositions":[
		"40",
		"18",
		"10",
		"21",
		"41",
		"4",
		"5",
		"11",
		"4",
		"25",
		"37",
		"9",
		"32",
		"15",
		"14",
		"40",
		"30",
		"16",
		"7",
		"27",
		"19",
		"38",
		"42",
		"10",
		"17"
	],
	"finishPositionsCount": "25",
	"finishes": "25",
	"points": "2785"
},
{
	"driverName": "J Burton",
	"carNumber": "99",
	"lapsCompleted": "3688",
	"lapsLed": "161",
	"dnfs": "3",
	"racesLed": "8",
	"startPositions":[
		"1",
		"16",
		"5",
		"30",
		"14",
		"4",
		"29",
		"3",
		"7",
		"18",
		"21",
		"1",
		"38",
		"11",
		"3",
		"40",
		"15",
		"7",
		"25",
		"11",
		"20",
		"34",
		"18",
		"43",
		"18"
	],
	"startPositionsCount": "25",
	"starts": "25",
	"finishPositions":[
		"6",
		"11",
		"8",
		"4",
		"1",
		"24",
		"7",
		"41",
		"1",
		"20",
		"3",
		"19",
		"40",
		"3",
		"12",
		"2",
		"15",
		"4",
		"14",
		"19",
		"4",
		"28",
		"2",
		"42",
		"10"
	],
	"finishPositionsCount": "25",
	"finishes": "25",
	"points": "3785"
},
{
	"driverName": "J Gordon",
	"carNumber": "24",
	"lapsCompleted": "3636",
	"lapsLed": "167",
	"dnfs": "3",
	"racesLed": "13",
	"startPositions":[
		"14",
		"4",
		"18",
		"3",
		"3",
		"5",
		"7",
		"1",
		"19",
		"4",
		"10",
		"17",
		"19",
		"2",
		"9",
		"10",
		"6",
		"11",
		"9",
		"2",
		"5",
		"10",
		"20",
		"5",
		"13"
	],
	"startPositionsCount": "25",
	"starts": "25",
	"finishPositions":[
		"37",
		"10",
		"17",
		"3",
		"22",
		"2",
		"40",
		"10",
		"23",
		"2",
		"41",
		"2",
		"23",
		"24",
		"13",
		"3",
		"26",
		"5",
		"2",
		"36",
		"23",
		"24",
		"1",
		"5",
		"5"
	],
	"finishPositionsCount": "25",
	"finishes": "25",
	"points": "3510"
},
{
	"driverName": "J Green",
	"carNumber": "30",
	"lapsCompleted": "3600",
	"lapsLed": "5",
	"dnfs": "1",
	"racesLed": "2",
	"startPositions":[
		"12",
		"17",
		"25",
		"42",
		"25",
		"7",
		"4",
		"22",
		"15",
		"15",
		"8",
		"19",
		"15",
		"21",
		"5",
		"14",
		"22",
		"18",
		"19",
		"43",
		"8",
		"8",
		"28",
		"28",
		"6"
	],
	"startPositionsCount": "25",
	"starts": "25",
	"finishPositions":[
		"24",
		"25",
		"7",
		"18",
		"38",
		"17",
		"20",
		"34",
		"25",
		"17",
		"43",
		"18",
		"21",
		"9",
		"7",
		"7",
		"24",
		"15",
		"12",
		"33",
		"35",
		"17",
		"41",
		"17",
		"14"
	],
	"finishPositionsCount": "25",
	"finishes": "25",
	"points": "2755"
},
{
	  "driverName": "J Haley",
	  "carNumber": "108",
	  "lapsCompleted": "751",
	  "lapsLed": "0",
	  "dnfs": "1",
	  "racesLed": "0",
	"startPositions":[
		"0",
		"39",
		"42",
		"0",
		"0",
		"0",
		"0",
		"0",
		"0",
		"0",
		"39",
		"0",
		"0",
		"39",
		"0",
		"0",
		"0",
		"0",
		"0",
		"0",
		"0",
		"0",
		"0",
		"0",
		"0"
	],
	  "startPositionsCount": "25",
	  "starts": "4",
	"finishPositions":[
		"0",
		"37",
		"40",
		"0",
		"0",
		"0",
		"0",
		"0",
		"0",
		"0",
		"34",
		"0",
		"0",
		"40",
		"0",
		"0",
		"0",
		"0",
		"0",
		"0",
		"0",
		"0",
		"0",
		"0",
		"0"
	],
  	"finishPositionsCount": "25",
	  "finishes": "4",
	  "points": "115"
},
{
	"driverName": "J Hedlesky",
	"carNumber": "90",
	"lapsCompleted": "146",
	"lapsLed": "0",
	"dnfs": "1",
	"racesLed": "0",
	"startPositions":[
		"0",
		"0",
		"43",
		"0",
		"0",
		"0",
		"0",
		"0",
		"0",
		"0",
		"0",
		"0",
		"0",
		"0",
		"0",
		"0",
		"0",
		"0",
		"0",
		"0",
		"0",
		"0",
		"0",
		"0",
		"30"
	],
	"startPositionsCount": "25",
	"starts": "2",
	"finishPositions":[
		"0",
		"0",
		"43",
		"0",
		"0",
		"0",
		"0",
		"0",
		"0",
		"0",
		"0",
		"0",
		"0",
		"0",
		"0",
		"0",
		"0",
		"0",
		"0",
		"0",
		"0",
		"0",
		"0",
		"0",
		"35"
	],
	"finishPositionsCount": "25",
	"finishes": "2",
	"points": "50"
},
{
	"driverName": "J Johnson",
	"carNumber": "48",
	"lapsCompleted": "3495",
	"lapsLed": "163",
	"dnfs": "2",
	"racesLed": "6",
	"startPositions":[
		"5",
		"5",
		"10",
		"9",
		"20",
		"15",
		"15",
		"12",
		"2",
		"10",
		"32",
		"4",
		"1",
		"15",
		"10",
		"20",
		"11",
		"4",
		"20",
		"24",
		"19",
		"2",
		"12",
		"2",
		"9"
	],
	"startPositionsCount": "25",
	"starts": "25",
	"finishPositions":[
		"9",
		"21",
		"12",
		"15",
		"14",
		"13",
		"11",
		"42",
		"8",
		"19",
		"20",
		"25",
		"3",
		"41",
		"8",
		"6",
		"33",
		"8",
		"18",
		"29",
		"3",
		"8",
		"19",
		"4",
		"3"
	],
	"finishPositionsCount": "25",
	"finishes": "25",
	"points": "3510"
},
{
	  "driverName": "J Lang",
	  "carNumber": "115",
	  "lapsCompleted": "340",
	  "lapsLed": "0",
	  "dnfs": "2",
	  "racesLed": "0",
	"startPositions":[
		"0",
		"35",
		"0",
		"0",
		"0",
		"38",
		"0",
		"0",
		"0",
		"0",
		"0",
		"0",
		"0",
		"0",
		"0",
		"0",
		"0",
		"37",
		"0",
		"0",
		"0",
		"0",
		"0",
		"0",
		"0"
	],
	  "startPositionsCount": "25",
	  "starts": "3",
	"finishPositions":[
		"0",
		"41",
		"0",
		"0",
		"0",
		"39",
		"0",
		"0",
		"0",
		"0",
		"0",
		"0",
		"0",
		"0",
		"0",
		"0",
		"0",
		"36",
		"0",
		"0",
		"0",
		"0",
		"0",
		"0",
		"0"
	],
  	"finishPositionsCount": "25",
	  "finishes": "3",
	  "points": "75"
},
{
	  "driverName": "J Masella",
	  "carNumber": "191",
	  "lapsCompleted": "423",
	  "lapsLed": "0",
	  "dnfs": "1",
	  "racesLed": "0",
	"startPositions":[
		"0",
		"0",
		"0",
		"0",
		"0",
		"0",
		"0",
		"0",
		"0",
		"0",
		"0",
		"32",
		"0",
		"0",
		"0",
		"29",
		"0",
		"0",
		"39",
		"0",
		"0",
		"0",
		"0",
		"0",
		"0"
	],
	  "startPositionsCount": "25",
	  "starts": "3",
	"finishPositions":[
		"0",
		"0",
		"0",
		"0",
		"0",
		"0",
		"0",
		"0",
		"0",
		"0",
		"0",
		"41",
		"0",
		"0",
		"0",
		"31",
		"0",
		"0",
		"41",
		"0",
		"0",
		"0",
		"0",
		"0",
		"0"
	],
  	"finishPositionsCount": "25",
	  "finishes": "3",
	  "points": "95"
},
{
	"driverName": "J Mayfield",
	"carNumber": "19",
	"lapsCompleted": "3493",
	"lapsLed": "24",
	"dnfs": "4",
	"racesLed": "2",
	"startPositions":[
		"22",
		"22",
		"19",
		"24",
		"9",
		"16",
		"1",
		"7",
		"23",
		"0",
		"28",
		"3",
		"28",
		"4",
		"28",
		"19",
		"23",
		"25",
		"8",
		"19",
		"34",
		"16",
		"16",
		"23",
		"25"
	],
	"startPositionsCount": "25",
	"starts": "24",
	"finishPositions":[
		"18",
		"30",
		"31",
		"24",
		"8",
		"29",
		"17",
		"30",
		"34",
		"0",
		"11",
		"13",
		"12",
		"16",
		"20",
		"8",
		"18",
		"19",
		"28",
		"11",
		"42",
		"42",
		"9",
		"25",
		"16"
	],
	"finishPositionsCount": "25",
	"finishes": "24",
	"points": "2700"
},
{
	"driverName": "J Nadeau",
	"carNumber": "01",
	"lapsCompleted": "3475",
	"lapsLed": "0",
	"dnfs": "2",
	"racesLed": "0",
	"startPositions":[
		"26",
		"42",
		"32",
		"34",
		"6",
		"36",
		"16",
		"38",
		"32",
		"22",
		"40",
		"9",
		"8",
		"18",
		"31",
		"2",
		"5",
		"15",
		"23",
		"15",
		"31",
		"3",
		"36",
		"0",
		"43"
	],
	"startPositionsCount": "25",
	"starts": "24",
	"finishPositions":[
		"26",
		"19",
		"18",
		"31",
		"30",
		"16",
		"32",
		"36",
		"43",
		"6",
		"28",
		"27",
		"36",
		"37",
		"40",
		"28",
		"31",
		"27",
		"15",
		"35",
		"25",
		"16",
		"7",
		"0",
		"24"
	],
	"finishPositionsCount": "25",
	"finishes": "24",
	"points": "2050"
},
{
	  "driverName": "J Nemechek",
	  "carNumber": "25",
	  "lapsCompleted": "2935",
	  "lapsLed": "0",
	  "dnfs": "1",
	  "racesLed": "0",
	"startPositions":[
		"32",
		"13",
		"33",
		"43",
		"0",
		"34",
		"42",
		"23",
		"37",
		"34",
		"36",
		"20",
		"40",
		"0",
		"29",
		"37",
		"37",
		"0",
		"0",
		"25",
		"36",
		"14",
		"38",
		"38",
		"0"
	],
	  "startPositionsCount": "25",
	  "starts": "20",
	"finishPositions":[
		"25",
		"27",
		"28",
		"35",
		"0",
		"42",
		"37",
		"16",
		"9",
		"34",
		"31",
		"40",
		"30",
		"0",
		"38",
		"29",
		"3",
		"0",
		"0",
		"26",
		"14",
		"19",
		"13",
		"37",
		"0"
	],
  	"finishPositionsCount": "25",
	  "finishes": "20",
	  "points": "1680"
},
{
	"driverName": "J Salerno",
	"carNumber": "168",
	"lapsCompleted": "408",
	"lapsLed": "0",
	"dnfs": "1",
	"racesLed": "0",
	"startPositions":[
		"0",
		"0",
		"0",
		"0",
		"0",
		"0",
		"0",
		"0",
		"0",
		"0",
		"0",
		"39",
		"0",
		"0",
		"0",
		"0",
		"0",
		"0",
		"0",
		"38",
		"0",
		"36",
		"0",
		"0",
		"36"
	],
	"startPositionsCount": "25",
	"starts": "4",
	"finishPositions":[
		"0",
		"0",
		"0",
		"0",
		"0",
		"0",
		"0",
		"0",
		"0",
		"0",
		"0",
		"43",
		"0",
		"0",
		"0",
		"0",
		"0",
		"0",
		"0",
		"32",
		"0",
		"40",
		"0",
		"0",
		"32"
	],
	"finishPositionsCount": "25",
	"finishes": "4",
	"points": "145"
},
{
	"driverName": "J Spencer",
	"carNumber": "7",
	"lapsCompleted": "3478",
	"lapsLed": "3",
	"dnfs": "2",
	"racesLed": "1",
	"startPositions":[
		"23",
		"7",
		"37",
		"35",
		"37",
		"18",
		"25",
		"36",
		"24",
		"35",
		"12",
		"43",
		"12",
		"33",
		"0",
		"25",
		"38",
		"17",
		"27",
		"37",
		"24",
		"35",
		"27",
		"40",
		"8"
	],
	"startPositionsCount": "25",
	"starts": "24",
	"finishPositions":[
		"29",
		"32",
		"35",
		"20",
		"32",
		"23",
		"19",
		"33",
		"15",
		"30",
		"27",
		"36",
		"25",
		"11",
		"0",
		"14",
		"41",
		"24",
		"22",
		"23",
		"37",
		"13",
		"20",
		"31",
		"42"
	],
	"finishPositionsCount": "25",
	"finishes": "24",
	"points": "2065"
},
{
	"driverName": "J Sprague",
	"carNumber": "0",
	"lapsCompleted": "3573",
	"lapsLed": "0",
	"dnfs": "1",
	"racesLed": "0",
	"startPositions":[
		"36",
		"28",
		"17",
		"22",
		"12",
		"41",
		"19",
		"14",
		"28",
		"28",
		"37",
		"22",
		"34",
		"24",
		"23",
		"33",
		"26",
		"29",
		"24",
		"34",
		"41",
		"0",
		"33",
		"36",
		"31"
	],
	"startPositionsCount": "25",
	"starts": "24",
	"finishPositions":[
		"5",
		"7",
		"38",
		"27",
		"13",
		"31",
		"33",
		"6",
		"12",
		"27",
		"25",
		"28",
		"17",
		"36",
		"34",
		"30",
		"28",
		"22",
		"32",
		"20",
		"16",
		"0",
		"35",
		"15",
		"26"
	],
	"finishPositionsCount": "25",
	"finishes": "24",
	"points": "2400"
},
{
	"driverName": "K Busch",
	"carNumber": "97",
	"lapsCompleted": "3733",
	"lapsLed": "704",
	"dnfs": "2",
	"racesLed": "13",
	"startPositions":[
		"2",
		"2",
		"3",
		"8",
		"2",
		"1",
		"8",
		"2",
		"5",
		"12",
		"2",
		"8",
		"10",
		"8",
		"1",
		"26",
		"1",
		"5",
		"6",
		"4",
		"25",
		"30",
		"1",
		"12",
		"27"
	],
	"startPositionsCount": "25",
	"starts": "25",
	"finishPositions":[
		"34",
		"16",
		"1",
		"2",
		"4",
		"9",
		"13",
		"1",
		"3",
		"14",
		"5",
		"4",
		"1",
		"5",
		"2",
		"1",
		"25",
		"2",
		"37",
		"34",
		"26",
		"25",
		"5",
		"2",
		"13"
	],
	"finishPositionsCount": "25",
	"finishes": "25",
	"points": "4095"
},
{
	"driverName": "K Harvick",
	"carNumber": "29",
	"lapsCompleted": "3727",
	"lapsLed": "3",
	"dnfs": "3",
	"racesLed": "1",
	"startPositions":[
		"21",
		"31",
		"27",
		"37",
		"15",
		"11",
		"28",
		"32",
		"11",
		"20",
		"33",
		"35",
		"13",
		"36",
		"40",
		"28",
		"32",
		"16",
		"5",
		"18",
		"9",
		"9",
		"22",
		"25",
		"34"
	],
	"startPositionsCount": "25",
	"starts": "25",
	"finishPositions":[
		"28",
		"24",
		"23",
		"19",
		"42",
		"35",
		"25",
		"32",
		"14",
		"22",
		"22",
		"21",
		"16",
		"29",
		"24",
		"37",
		"10",
		"11",
		"10",
		"8",
		"39",
		"27",
		"18",
		"9",
		"27"
	],
	"finishPositionsCount": "25",
	"finishes": "25",
	"points": "2580"
},
{
	  "driverName": "K Iannarelli",
	  "carNumber": "170",
	  "lapsCompleted": "675",
	  "lapsLed": "0",
	  "dnfs": "1",
	  "racesLed": "0",
	"startPositions":[
		"0",
		"0",
		"0",
		"0",
		"0",
		"39",
		"0",
		"0",
		"0",
		"0",
		"43",
		"0",
		"0",
		"0",
		"0",
		"0",
		"0",
		"0",
		"0",
		"0",
		"0",
		"38",
		"0",
		"0",
		"0"
	],
	  "startPositionsCount": "25",
	  "starts": "3",
	"finishPositions":[
		"0",
		"0",
		"0",
		"0",
		"0",
		"19",
		"0",
		"0",
		"0",
		"0",
		"36",
		"0",
		"0",
		"0",
		"0",
		"0",
		"0",
		"0",
		"0",
		"0",
		"0",
		"29",
		"0",
		"0",
		"0"
	],
  	"finishPositionsCount": "25",
	  "finishes": "3",
	  "points": "235"
},
{
	"driverName": "K Petty",
	"carNumber": "45",
	"lapsCompleted": "3656",
	"lapsLed": "8",
	"dnfs": "3",
	"racesLed": "2",
	"startPositions":[
		"25",
		"40",
		"39",
		"6",
		"16",
		"14",
		"39",
		"29",
		"35",
		"24",
		"24",
		"37",
		"29",
		"25",
		"21",
		"15",
		"35",
		"20",
		"16",
		"36",
		"28",
		"33",
		"17",
		"21",
		"16"
	],
	"startPositionsCount": "25",
	"starts": "25",
	"finishPositions":[
		"41",
		"9",
		"24",
		"11",
		"34",
		"30",
		"26",
		"5",
		"29",
		"36",
		"35",
		"23",
		"43",
		"7",
		"17",
		"22",
		"23",
		"30",
		"25",
		"39",
		"31",
		"6",
		"38",
		"22",
		"25"
	],
	"finishPositionsCount": "25",
	"finishes": "25",
	"points": "2290"
},
{
	"driverName": "K Schrader",
	"carNumber": "49",
	"lapsCompleted": "3281",
	"lapsLed": "0",
	"dnfs": "5",
	"racesLed": "0",
	"startPositions":[
		"13",
		"24",
		"16",
		"38",
		"32",
		"27",
		"27",
		"37",
		"40",
		"32",
		"25",
		"0",
		"0",
		"34",
		"14",
		"22",
		"42",
		"33",
		"38",
		"16",
		"23",
		"22",
		"24",
		"13",
		"42"
	],
	"startPositionsCount": "25",
	"starts": "23",
	"finishPositions":[
		"14",
		"33",
		"26",
		"38",
		"27",
		"34",
		"41",
		"40",
		"28",
		"31",
		"33",
		"0",
		"0",
		"22",
		"37",
		"32",
		"9",
		"29",
		"31",
		"16",
		"40",
		"30",
		"31",
		"24",
		"29"
	],
	"finishPositionsCount": "25",
	"finishes": "23",
	"points": "1620"
},
{
	"driverName": "K Wallace",
	"carNumber": "23",
	"lapsCompleted": "3216",
	"lapsLed": "1",
	"dnfs": "1",
	"racesLed": "1",
	"startPositions":[
		"0",
		"38",
		"23",
		"26",
		"29",
		"22",
		"0",
		"43",
		"38",
		"0",
		"16",
		"24",
		"21",
		"41",
		"0",
		"23",
		"13",
		"14",
		"0",
		"29",
		"13",
		"42",
		"25",
		"32",
		"19"
	],
	"startPositionsCount": "25",
	"starts": "20",
	"finishPositions":[
		"0",
		"23",
		"34",
		"40",
		"25",
		"18",
		"0",
		"24",
		"35",
		"0",
		"30",
		"39",
		"27",
		"30",
		"0",
		"33",
		"2",
		"25",
		"0",
		"21",
		"13",
		"4",
		"30",
		"23",
		"38"
	],
	"finishPositionsCount": "25",
	"finishes": "20",
	"points": "1820"
},
{
	"driverName": "M Kenseth",
	"carNumber": "17",
	"lapsCompleted": "3682",
	"lapsLed": "57",
	"dnfs": "3",
	"racesLed": "6",
	"startPositions":[
		"17",
		"6",
		"9",
		"20",
		"11",
		"10",
		"17",
		"19",
		"20",
		"9",
		"7",
		"15",
		"18",
		"22",
		"13",
		"6",
		"18",
		"24",
		"10",
		"21",
		"6",
		"19",
		"13",
		"19",
		"14"
	],
	"startPositionsCount": "25",
	"starts": "25",
	"finishPositions":[
		"35",
		"13",
		"13",
		"14",
		"9",
		"7",
		"22",
		"8",
		"16",
		"16",
		"4",
		"5",
		"10",
		"6",
		"10",
		"39",
		"13",
		"40",
		"27",
		"25",
		"6",
		"26",
		"8",
		"20",
		"19"
	],
	"finishPositionsCount": "25",
	"finishes": "25",
	"points": "3410"
},
{
	  "driverName": "M La Terza",
	  "carNumber": "124",
	  "lapsCompleted": "571",
	  "lapsLed": "0",
	  "dnfs": "0",
	  "racesLed": "0",
	"startPositions":[
		"0",
		"0",
		"40",
		"0",
		"0",
		"0",
		"0",
		"0",
		"0",
		"0",
		"0",
		"0",
		"0",
		"0",
		"0",
		"0",
		"40",
		"0",
		"0",
		"0",
		"0",
		"28",
		"0",
		"0",
		"0"
	],
	  "startPositionsCount": "25",
	  "starts": "3",
	"finishPositions":[
		"0",
		"0",
		"41",
		"0",
		"0",
		"0",
		"0",
		"0",
		"0",
		"0",
		"0",
		"0",
		"0",
		"0",
		"0",
		"0",
		"11",
		"0",
		"0",
		"0",
		"0",
		"23",
		"0",
		"0",
		"0"
	],
  	"finishPositionsCount": "25",
	  "finishes": "3",
	  "points": "285"
},
{
	"driverName": "M Martin",
	"carNumber": "6",
	"lapsCompleted": "3816",
	"lapsLed": "447",
	"dnfs": "1",
	"racesLed": "14",
	"startPositions":[
		"11",
		"11",
		"8",
		"10",
		"4",
		"3",
		"38",
		"4",
		"1",
		"3",
		"27",
		"5",
		"20",
		"6",
		"7",
		"8",
		"2",
		"1",
		"3",
		"3",
		"3",
		"32",
		"6",
		"7",
		"2"
	],
	"startPositionsCount": "25",
	"starts": "25",
	"finishPositions":[
		"36",
		"3",
		"5",
		"39",
		"26",
		"10",
		"1",
		"3",
		"13",
		"12",
		"21",
		"1",
		"28",
		"1",
		"19",
		"5",
		"37",
		"3",
		"5",
		"3",
		"17",
		"11",
		"11",
		"14",
		"1"
	],
	"finishPositionsCount": "25",
	"finishes": "25",
	"points": "3890"
},
{
	"driverName": "M Skinner",
	"carNumber": "4",
	"lapsCompleted": "3359",
	"lapsLed": "0",
	"dnfs": "4",
	"racesLed": "0",
	"startPositions":[
		"38",
		"43",
		"31",
		"7",
		"30",
		"30",
		"36",
		"25",
		"18",
		"31",
		"23",
		"34",
		"42",
		"23",
		"36",
		"0",
		"24",
		"36",
		"21",
		"32",
		"11",
		"7",
		"26",
		"16",
		"32"
	],
	"startPositionsCount": "25",
	"starts": "24",
	"finishPositions":[
		"20",
		"31",
		"30",
		"25",
		"43",
		"32",
		"36",
		"23",
		"38",
		"32",
		"18",
		"31",
		"26",
		"33",
		"28",
		"0",
		"32",
		"31",
		"29",
		"22",
		"21",
		"35",
		"24",
		"26",
		"22"
	],
	"finishPositionsCount": "25",
	"finishes": "24",
	"points": "1775"
},
{
	  "driverName": "M Stackpole",
	  "carNumber": "190",
	  "lapsCompleted": "607",
	  "lapsLed": "0",
	  "dnfs": "1",
	  "racesLed": "0",
	"startPositions":[
		"0",
		"0",
		"0",
		"0",
		"0",
		"0",
		"41",
		"0",
		"43",
		"0",
		"0",
		"0",
		"39",
		"0",
		"0",
		"42",
		"0",
		"40",
		"0",
		"0",
		"0",
		"0",
		"0",
		"0",
		"0"
	],
	  "startPositionsCount": "25",
	  "starts": "5",
	"finishPositions":[
		"0",
		"0",
		"0",
		"0",
		"0",
		"0",
		"34",
		"0",
		"41",
		"0",
		"0",
		"0",
		"39",
		"0",
		"0",
		"34",
		"0",
		"42",
		"0",
		"0",
		"0",
		"0",
		"0",
		"0",
		"0"
	],
  	"finishPositionsCount": "25",
	  "finishes": "5",
	  "points": "145"
},
{
	"driverName": "M Waltrip",
	"carNumber": "15",
	"lapsCompleted": "3470",
	"lapsLed": "7",
	"dnfs": "1",
	"racesLed": "3",
	"startPositions":[
		"10",
		"14",
		"24",
		"11",
		"34",
		"35",
		"22",
		"10",
		"21",
		"14",
		"20",
		"42",
		"26",
		"27",
		"27",
		"43",
		"29",
		"9",
		"35",
		"13",
		"15",
		"39",
		"14",
		"9",
		"29"
	],
	"startPositionsCount": "25",
	"starts": "25",
	"finishPositions":[
		"7",
		"36",
		"16",
		"10",
		"18",
		"40",
		"23",
		"9",
		"7",
		"21",
		"10",
		"15",
		"6",
		"0",
		"3",
		"26",
		"16",
		"41",
		"11",
		"7",
		"38",
		"22",
		"3",
		"18",
		"2"
	],
	"finishPositionsCount": "25",
	"finishes": "24",
	"points": "3215"
},
{
	"driverName": "P Inglis",
	"carNumber": "144",
	"lapsCompleted": "465",
	"lapsLed": "0",
	"dnfs": "0",
	"racesLed": "0",
	"startPositions":[
		"40",
		"0",
		"0",
		"0",
		"0",
		"0",
		"0",
		"0",
		"0",
		"0",
		"0",
		"0",
		"0",
		"0",
		"0",
		"0",
		"0",
		"42",
		"0",
		"0",
		"0",
		"0",
		"0",
		"24",
		"33"
	],
	"startPositionsCount": "25",
	"starts": "4",
	"finishPositions":[
		"16",
		"0",
		"0",
		"0",
		"0",
		"0",
		"0",
		"0",
		"0",
		"0",
		"0",
		"0",
		"0",
		"0",
		"0",
		"0",
		"0",
		"38",
		"0",
		"0",
		"0",
		"0",
		"0",
		"34",
		"33"
	],
	"finishPositionsCount": "25",
	"finishes": "4",
	"points": "275"
},
{
	"driverName": "R Craven",
	"carNumber": "32",
	"lapsCompleted": "3505",
	"lapsLed": "12",
	"dnfs": "3",
	"racesLed": "4",
	"startPositions":[
		"33",
		"9",
		"13",
		"31",
		"17",
		"8",
		"2",
		"16",
		"14",
		"7",
		"38",
		"7",
		"24",
		"28",
		"25",
		"17",
		"30",
		"23",
		"34",
		"10",
		"17",
		"12",
		"11",
		"11",
		"3"
	],
	"startPositionsCount": "25",
	"starts": "25",
	"finishPositions":[
		"30",
		"14",
		"29",
		"17",
		"33",
		"38",
		"16",
		"21",
		"37",
		"3",
		"15",
		"38",
		"33",
		"10",
		"21",
		"18",
		"7",
		"18",
		"4",
		"6",
		"15",
		"39",
		"27",
		"12",
		"4"
	],
	"finishPositionsCount": "25",
	"finishes": "25",
	"points": "2930"
},
{
	"driverName": "R Gordon",
	"carNumber": "31",
	"lapsCompleted": "3539",
	"lapsLed": "5",
	"dnfs": "6",
	"racesLed": "1",
	"startPositions":[
		"16",
		"12",
		"7",
		"23",
		"39",
		"31",
		"23",
		"40",
		"8",
		"21",
		"29",
		"25",
		"2",
		"43",
		"8",
		"34",
		"19",
		"19",
		"12",
		"42",
		"16",
		"25",
		"8",
		"29",
		"22"
	],
	"startPositionsCount": "25",
	"starts": "25",
	"finishPositions":[
		"42",
		"39",
		"37",
		"30",
		"28",
		"36",
		"9",
		"12",
		"2",
		"24",
		"19",
		"20",
		"34",
		"18",
		"26",
		"23",
		"4",
		"43",
		"16",
		"42",
		"11",
		"20",
		"40",
		"7",
		"40"
	],
	"finishPositionsCount": "25",
	"finishes": "25",
	"points": "2330"
},
{
	"driverName": "R Newman",
	"carNumber": "12",
	"lapsCompleted": "3628",
	"lapsLed": "36",
	"dnfs": "2",
	"racesLed": "6",
	"startPositions":[
		"8",
		"19",
		"20",
		"14",
		"18",
		"6",
		"14",
		"6",
		"16",
		"37",
		"5",
		"13",
		"7",
		"42",
		"16",
		"30",
		"16",
		"8",
		"4",
		"5",
		"22",
		"27",
		"7",
		"10",
		"10"
	],
	"startPositionsCount": "25",
	"starts": "25",
	"finishPositions":[
		"2",
		"4",
		"3",
		"13",
		"2",
		"20",
		"12",
		"2",
		"18",
		"26",
		"7",
		"17",
		"24",
		"21",
		"4",
		"20",
		"43",
		"6",
		"26",
		"14",
		"8",
		"9",
		"32",
		"13",
		"7"
	],
	"finishPositionsCount": "25",
	"finishes": "25",
	"points": "3700"
},
{
	  "driverName": "R Pantano",
	  "carNumber": "155",
	  "lapsCompleted": "720",
	  "lapsLed": "0",
	  "dnfs": "0",
	  "racesLed": "0",
	"startPositions":[
		"0",
		"0",
		"0",
		"0",
		"0",
		"0",
		"0",
		"35",
		"0",
		"0",
		"0",
		"0",
		"27",
		"0",
		"35",
		"24",
		"0",
		"0",
		"0",
		"0",
		"0",
		"0",
		"0",
		"0",
		"0"
	],
	  "startPositionsCount": "25",
	  "starts": "4",
	"finishPositions":[
		"0",
		"0",
		"0",
		"0",
		"0",
		"0",
		"0",
		"25",
		"0",
		"0",
		"0",
		"0",
		"38",
		"0",
		"36",
		"36",
		"0",
		"0",
		"0",
		"0",
		"0",
		"0",
		"0",
		"0",
		"0"
	],
  	"finishPositionsCount": "25",
	  "finishes": "4",
	  "points": "190"
},
{
	"driverName": "R Rudd",
	"carNumber": "21",
	"lapsCompleted": "3583",
	"lapsLed": "87",
	"dnfs": "3",
	"racesLed": "7",
	"startPositions":[
		"7",
		"33",
		"29",
		"19",
		"21",
		"12",
		"9",
		"9",
		"22",
		"5",
		"14",
		"12",
		"6",
		"17",
		"18",
		"21",
		"17",
		"12",
		"11",
		"6",
		"12",
		"13",
		"19",
		"4",
		"1"
	],
	"startPositionsCount": "25",
	"starts": "25",
	"finishPositions":[
		"17",
		"1",
		"4",
		"8",
		"16",
		"28",
		"39",
		"7",
		"11",
		"10",
		"39",
		"7",
		"8",
		"4",
		"18",
		"16",
		"36",
		"7",
		"3",
		"4",
		"2",
		"41",
		"23",
		"3",
		"41"
	],
	"finishPositionsCount": "25",
	"finishes": "25",
	"points": "3505"
},
{
	"driverName": "R Wallace",
	"carNumber": "2",
	"lapsCompleted": "3594",
	"lapsLed": "114",
	"dnfs": "2",
	"racesLed": "5",
	"startPositions":[
		"15",
		"26",
		"2",
		"21",
		"24",
		"9",
		"6",
		"34",
		"25",
		"11",
		"4",
		"33",
		"9",
		"9",
		"19",
		"4",
		"7",
		"3",
		"26",
		"8",
		"35",
		"5",
		"4",
		"22",
		"11"
	],
	"startPositionsCount": "25",
	"starts": "25",
	"finishPositions":[
		"8",
		"6",
		"11",
		"5",
		"5",
		"1",
		"14",
		"43",
		"10",
		"18",
		"6",
		"22",
		"4",
		"8",
		"15",
		"17",
		"40",
		"33",
		"8",
		"9",
		"18",
		"37",
		"29",
		"8",
		"18"
	],
	"finishPositionsCount": "25",
	"finishes": "25",
	"points": "3495"
},
{
	  "driverName": "R Young",
	  "carNumber": "119",
	  "lapsCompleted": "269",
	  "lapsLed": "0",
	  "dnfs": "1",
	  "racesLed": "0",
	"startPositions":[
		"0",
		"0",
		"0",
		"0",
		"0",
		"0",
		"0",
		"41",
		"0",
		"0",
		"0",
		"0",
		"0",
		"0",
		"0",
		"0",
		"0",
		"0",
		"42",
		"33",
		"0",
		"0",
		"0",
		"0",
		"0"
	],
	  "startPositionsCount": "25",
	  "starts": "3",
	"finishPositions":[
		"0",
		"0",
		"0",
		"0",
		"0",
		"0",
		"0",
		"35",
		"0",
		"0",
		"0",
		"0",
		"0",
		"0",
		"0",
		"0",
		"0",
		"0",
		"40",
		"17",
		"0",
		"0",
		"0",
		"0",
		"0"
	],
  	"finishPositionsCount": "25",
	  "finishes": "3",
	  "points": "200"
},
{
	  "driverName": "S Myers",
	  "carNumber": "127",
	  "lapsCompleted": "67",
	  "lapsLed": "0",
	  "dnfs": "1",
	  "racesLed": "0",
	"startPositions":[
		"0",
		"0",
		"0",
		"0",
		"0",
		"0",
		"0",
		"0",
		"0",
		"0",
		"0",
		"0",
		"0",
		"0",
		"0",
		"0",
		"0",
		"0",
		"0",
		"0",
		"0",
		"0",
		"0",
		"33",
		"0"
	],
	  "startPositionsCount": "25",
	  "starts": "1",
	"finishPositions":[
		"0",
		"0",
		"0",
		"0",
		"0",
		"0",
		"0",
		"0",
		"0",
		"0",
		"0",
		"0",
		"0",
		"0",
		"0",
		"0",
		"0",
		"0",
		"0",
		"0",
		"0",
		"0",
		"0",
		"43",
		"0"
	],
  	"finishPositionsCount": "25",
	  "finishes": "1",
	  "points": "5"
},
{
	"driverName": "S Park",
	"carNumber": "1",
	"lapsCompleted": "3432",
	"lapsLed": "87",
	"dnfs": "4",
	"racesLed": "1",
	"startPositions":[
		"19",
		"37",
		"22",
		"15",
		"22",
		"40",
		"33",
		"31",
		"17",
		"16",
		"13",
		"16",
		"30",
		"10",
		"34",
		"18",
		"8",
		"27",
		"30",
		"9",
		"42",
		"6",
		"23",
		"39",
		"21"
	],
	"startPositionsCount": "25",
	"starts": "25",
	"finishPositions":[
		"39",
		"26",
		"33",
		"37",
		"3",
		"3",
		"24",
		"18",
		"20",
		"5",
		"42",
		"12",
		"11",
		"17",
		"31",
		"38",
		"19",
		"28",
		"30",
		"12",
		"30",
		"10",
		"37",
		"36",
		"21"
	],
	"finishPositionsCount": "25",
	"finishes": "25",
	"points": "2535"
},
{
	  "driverName": "S Vandergriff",
	  "carNumber": "135",
	  "lapsCompleted": "199",
	  "lapsLed": "0",
	  "dnfs": "1",
	  "racesLed": "0",
	"startPositions":[
		"42",
		"0",
		"0",
		"0",
		"0",
		"0",
		"0",
		"42",
		"0",
		"0",
		"0",
		"0",
		"0",
		"0",
		"0",
		"0",
		"0",
		"0",
		"0",
		"0",
		"0",
		"0",
		"0",
		"0",
		"0"
	],
	  "startPositionsCount": "25",
	  "starts": "2",
	"finishPositions":[
		"43",
		"0",
		"0",
		"0",
		"0",
		"0",
		"0",
		"38",
		"0",
		"0",
		"0",
		"0",
		"0",
		"0",
		"0",
		"0",
		"0",
		"0",
		"0",
		"0",
		"0",
		"0",
		"0",
		"0",
		"0"
	],
  	"finishPositionsCount": "25",
	  "finishes": "2",
	  "points": "35"
},
{
	"driverName": "S Wimmer",
	"carNumber": "27",
	"lapsCompleted": "3535",
	"lapsLed": "0",
	"dnfs": "2",
	"racesLed": "0",
	"startPositions":[
		"24",
		"0",
		"14",
		"12",
		"7",
		"42",
		"30",
		"27",
		"29",
		"19",
		"18",
		"36",
		"36",
		"30",
		"24",
		"27",
		"21",
		"31",
		"14",
		"27",
		"37",
		"41",
		"37",
		"20",
		"39"
	],
	"startPositionsCount": "25",
	"starts": "24",
	"finishPositions":[
		"15",
		"0",
		"32",
		"23",
		"39",
		"26",
		"30",
		"17",
		"33",
		"9",
		"26",
		"32",
		"31",
		"13",
		"29",
		"24",
		"5",
		"20",
		"43",
		"40",
		"28",
		"31",
		"15",
		"33",
		"23"
	],
	"finishPositionsCount": "25",
	"finishes": "24",
	"points": "2130"
},
{
	  "driverName": "T Anita",
	  "carNumber": "111",
	  "lapsCompleted": "310",
	  "lapsLed": "0",
	  "dnfs": "0",
	  "racesLed": "0",
	"startPositions":[
		"0",
		"0",
		"0",
		"0",
		"35",
		"0",
		"40",
		"0",
		"0",
		"0",
		"0",
		"0",
		"0",
		"0",
		"0",
		"0",
		"0",
		"0",
		"0",
		"0",
		"0",
		"0",
		"0",
		"0",
		"0"
	],
	  "startPositionsCount": "25",
	  "starts": "2",
	"finishPositions":[
		"0",
		"0",
		"0",
		"0",
		"40",
		"0",
		"35",
		"0",
		"0",
		"0",
		"0",
		"0",
		"0",
		"0",
		"0",
		"0",
		"0",
		"0",
		"0",
		"0",
		"0",
		"0",
		"0",
		"0",
		"0"
	],
  	"finishPositionsCount": "25",
	  "finishes": "2",
	  "points": "60"
},
{
	"driverName": "T Labonte",
	"carNumber": "5",
	"lapsCompleted": "3669",
	"lapsLed": "0",
	"dnfs": "2",
	"racesLed": "0",
	"startPositions":[
		"35",
		"25",
		"38",
		"27",
		"27",
		"26",
		"26",
		"17",
		"34",
		"0",
		"35",
		"30",
		"35",
		"31",
		"15",
		"11",
		"33",
		"41",
		"15",
		"39",
		"10",
		"18",
		"29",
		"35",
		"40"
	],
	"startPositionsCount": "25",
	"starts": "24",
	"finishPositions":[
		"22",
		"8",
		"15",
		"36",
		"15",
		"15",
		"27",
		"37",
		"21",
		"0",
		"16",
		"30",
		"22",
		"19",
		"23",
		"43",
		"39",
		"17",
		"20",
		"28",
		"10",
		"14",
		"4",
		"40",
		"11"
	],
	"finishPositionsCount": "25",
	"finishes": "24",
	"points": "2585"
},
{
	  "driverName": "T Reils",
	  "carNumber": "153",
	  "lapsCompleted": "347",
	  "lapsLed": "0",
	  "dnfs": "0",
	  "racesLed": "0",
	"startPositions":[
		"0",
		"0",
		"0",
		"36",
		"0",
		"0",
		"0",
		"0",
		"0",
		"0",
		"0",
		"0",
		"0",
		"0",
		"0",
		"0",
		"0",
		"0",
		"0",
		"40",
		"38",
		"0",
		"0",
		"0",
		"0"
	],
	  "startPositionsCount": "25",
	  "starts": "3",
	"finishPositions":[
		"0",
		"0",
		"0",
		"43",
		"0",
		"0",
		"0",
		"0",
		"0",
		"0",
		"0",
		"0",
		"0",
		"0",
		"0",
		"0",
		"0",
		"0",
		"0",
		"30",
		"36",
		"0",
		"0",
		"0",
		"0"
	],
  	"finishPositionsCount": "25",
	  "finishes": "3",
	  "points": "115"
},
{
	"driverName": "T Stewart",
	"carNumber": "20",
	"lapsCompleted": "3633",
	"lapsLed": "167",
	"dnfs": "2",
	"racesLed": "11",
	"startPositions":[
		"3",
		"3",
		"30",
		"25",
		"13",
		"2",
		"3",
		"15",
		"10",
		"8",
		"3",
		"2",
		"14",
		"1",
		"17",
		"3",
		"12",
		"10",
		"2",
		"7",
		"26",
		"17",
		"5",
		"31",
		"23"
	],
	"startPositionsCount": "25",
	"starts": "25",
	"finishPositions":[
		"19",
		"2",
		"2",
		"7",
		"23",
		"25",
		"15",
		"4",
		"26",
		"15",
		"2",
		"3",
		"35",
		"23",
		"6",
		"42",
		"34",
		"10",
		"1",
		"2",
		"43",
		"1",
		"14",
		"11",
		"8"
	],
	"finishPositionsCount": "25",
	"finishes": "25",
	"points": "3630"
},
{
	"driverName": "W Burton",
	"carNumber": "22",
	"lapsCompleted": "3419",
	"lapsLed": "3",
	"dnfs": "1",
	"racesLed": "1",
	"startPositions":[
		"0",
		"34",
		"11",
		"28",
		"40",
		"33",
		"21",
		"28",
		"30",
		"25",
		"9",
		"0",
		"16",
		"19",
		"33",
		"9",
		"31",
		"35",
		"29",
		"0",
		"18",
		"26",
		"34",
		"15",
		"4"
	],
	"startPositionsCount": "25",
	"starts": "22",
	"finishPositions":[
		"0",
		"20",
		"25",
		"12",
		"29",
		"11",
		"6",
		"29",
		"40",
		"33",
		"13",
		"0",
		"9",
		"14",
		"30",
		"25",
		"38",
		"39",
		"13",
		"0",
		"34",
		"21",
		"10",
		"21",
		"9"
	],
	"finishPositionsCount": "25",
	"finishes": "22",
	"points": "2375"
}
  ]
}
